tabensemb/__init__.py
tabensemb/config/__init__.py
tabensemb/config/default.py
tabensemb/config/user_config.py
tabensemb/data/__init__.py
tabensemb/data/base.py
tabensemb/data/dataderiver.py
tabensemb/data/dataimputer.py
tabensemb/data/datamodule.py
tabensemb/data/dataprocessor.py
tabensemb/data/datasplitter.py
tabensemb/data/utils.py
tabensemb/model/__init__.py
tabensemb/model/autogluon.py
tabensemb/model/base.py
tabensemb/model/pytorch_tabular.py
tabensemb/model/sample.py
tabensemb/model/util_model.py
tabensemb/model/widedeep.py
tabensemb/model/_autogluon/__init__.py
tabensemb/model/_autogluon/multilabel.py
tabensemb/model/_pytorch_tabular/__init__.py
tabensemb/model/_pytorch_tabular/mute_track.py
tabensemb/model/_sample/__init__.py
tabensemb/model/_sample/cat_embed.py
tabensemb/model/_sample/require_model.py
tabensemb/model/_widedeep/__init__.py
tabensemb/model/_widedeep/widedeep_callback.py
tabensemb/trainer/__init__.py
tabensemb/trainer/trainer.py
tabensemb/trainer/utils.py
tabensemb/utils/__init__.py
tabensemb/utils/collate.py
tabensemb/utils/ranking.py
tabensemb/utils/utils.py
tabensemb/utils/imputers/__init__.py
tabensemb/utils/imputers/gain.py
tabensemb/utils/processors/__init__.py
tabensemb/utils/processors/rfecv.py
tabensemb-0.3.dist-info/LICENSE
tabensemb-0.3.dist-info/METADATA
tabensemb-0.3.dist-info/WHEEL
tabensemb-0.3.dist-info/top_level.txt
tabensemb-0.3.dist-info/RECORD
