Metadata-Version: 2.2
Name: tabensemb
Version: 0.3
Summary: A framework to ensemble model bases and evaluate various models for tabular predictions.
Home-page: https://github.com/Luwen-Zhang/tabular_ensemble
Author: Luwen-Zhang's Group at SJTU
Requires-Python: >=3.8.0
License-File: LICENSE
Requires-Dist: autogluon.tabular[all]<1.0.0,>=0.8.2
Requires-Dist: autogluon.common<1.0.0,>=0.8.2
Requires-Dist: autogluon.core<1.0.0,>=0.8.2
Requires-Dist: autogluon.features<1.0.0,>=0.8.2
Requires-Dist: captum>=0.6.0
Requires-Dist: gensim<4.3.3,>=4.3.0
Requires-Dist: matplotlib>=3.8.2
Requires-Dist: numba<0.58.2,>=0.58.0
Requires-Dist: numpy>=1.26.2
Requires-Dist: opencv-contrib-python<4.8.2,>=4.8.0
Requires-Dist: openpyxl>=3.1.2
Requires-Dist: pandas>=1.5.3
Requires-Dist: scikit-learn<1.4,>=1.2.2
Requires-Dist: scikit-optimize>=0.9.0
Requires-Dist: scipy>=1.11.4
Requires-Dist: seaborn>=0.13.0
Requires-Dist: statsmodels<0.14.1,>=0.14.0
Requires-Dist: tqdm>=4.66.1
Requires-Dist: torchmetrics>=0.11.4
Requires-Dist: pytorch-widedeep<1.6.2,>=1.3.2
Requires-Dist: pytorch-tabnet>=4.0
Requires-Dist: pytorch-tabular>=1.0.2
Requires-Dist: ray>=2.3.1
Requires-Dist: miceforest>=5.7.0
Requires-Dist: shap>=0.43.0
Requires-Dist: einops>=0.6.1
Requires-Dist: pytorch-lightning<2.0.0,>=1.9.5
Requires-Dist: traitlets>=5.9.0
Provides-Extra: torch
Requires-Dist: torch>=1.12.0; extra == "torch"
Provides-Extra: test
Requires-Dist: torch>=1.12.0; extra == "test"
Requires-Dist: pytest; extra == "test"
Requires-Dist: pytest-cov; extra == "test"
Requires-Dist: pytest-order; extra == "test"
Requires-Dist: pytest-mock; extra == "test"
Requires-Dist: black; extra == "test"
Provides-Extra: doc
Requires-Dist: sphinx==7.2.5; extra == "doc"
Requires-Dist: sphinx_rtd_theme==1.3.0; extra == "doc"
Requires-Dist: nbsphinx==0.9.3; extra == "doc"
Requires-Dist: pandoc==2.3; extra == "doc"
Requires-Dist: myst-parser==2.0.0; extra == "doc"
Requires-Dist: sphinx_copybutton==0.5.2; extra == "doc"
Requires-Dist: sphinx_paramlinks==0.6.0; extra == "doc"
Requires-Dist: numpydoc==1.5.0; extra == "doc"
Requires-Dist: pydata_sphinx_theme==0.13.3; extra == "doc"
Provides-Extra: notebook
Requires-Dist: jupyter; extra == "notebook"
Requires-Dist: notebook<7.0.0; extra == "notebook"
Dynamic: author
Dynamic: description
Dynamic: description-content-type
Dynamic: home-page
Dynamic: provides-extra
Dynamic: requires-dist
Dynamic: requires-python
Dynamic: summary
